setup.cfg
setup.py
pymysqlrpc/__init__.py
pymysqlrpc/logicerror.py
pymysqlrpc/rpchandler.py
pymysqlrpc/rpcserver.py
pymysqlrpc/utils.py
pymysqlrpc.egg-info/PKG-INFO
pymysqlrpc.egg-info/SOURCES.txt
pymysqlrpc.egg-info/dependency_links.txt
pymysqlrpc.egg-info/entry_points.txt
pymysqlrpc.egg-info/not-zip-safe
pymysqlrpc.egg-info/top_level.txt