Metadata-Version: 1.0
Name: pymysqlrpc
Version: 0.1.1
Summary: a rpc framework implement mysql server protocol on top of gevent
Home-page: http://github.com/feihuroger/pymysqlrpc
Author: roger.luo
Author-email: feihu.roger@gmail.com
License: MIT
Keywords: gevent mysql rpc
Platform: UNKNOWN
